<?xml version="1.0"?>
<manuscript>
  <url>https://digi.vatlib.it/view/MSS_Vat.gr.1209</url>
  <title>Codex Vaticanus</title>
  <shelfmark>MSS Vat.gr.1209</shelfmark>
  <quire n="1">
    <leaf n="1" mode="original" single="false" folio_number="1" conjoin="10" position="1" opposite="10"/>
    <leaf n="2" mode="original" single="false" folio_number="2" conjoin="9" position="2" opposite="9"/>
    <leaf n="3" mode="original" single="false" folio_number="3" conjoin="8" position="3" opposite="8"/>
    <leaf n="4" mode="original" single="false" folio_number="4" conjoin="7" position="4" opposite="7"/>
    <leaf n="5" mode="original" single="false" folio_number="5" conjoin="6" position="5" opposite="6"/>
    <leaf n="6" mode="original" single="false" folio_number="6" conjoin="5" position="6" opposite="5"/>
    <leaf n="7" mode="original" single="false" folio_number="7" conjoin="4" position="7" opposite="4"/>
    <leaf n="8" mode="original" single="false" folio_number="8" conjoin="3" position="8" opposite="3"/>
    <leaf n="9" mode="original" single="false" folio_number="9" conjoin="2" position="9" opposite="2"/>
    <leaf n="10" mode="original" single="false" folio_number="10" conjoin="1" position="10" opposite="1"/>
  </quire>
  <quire n="2">
    <leaf n="1" mode="original" single="false" folio_number="11" conjoin="10" position="1" opposite="10"/>
    <leaf n="2" mode="original" single="false" folio_number="12" conjoin="9" position="2" opposite="9"/>
    <leaf n="3" mode="original" single="false" folio_number="13" conjoin="8" position="3" opposite="8"/>
    <leaf n="4" mode="original" single="false" folio_number="14" conjoin="7" position="4" opposite="7"/>
    <leaf n="5" mode="original" single="false" folio_number="15" conjoin="6" position="5" opposite="6"/>
    <leaf n="6" mode="original" single="false" folio_number="16" conjoin="5" position="6" opposite="5"/>
    <leaf n="7" mode="original" single="false" folio_number="17" conjoin="4" position="7" opposite="4"/>
    <leaf n="8" mode="original" single="false" folio_number="18" conjoin="3" position="8" opposite="3"/>
    <leaf n="9" mode="original" single="false" folio_number="19" conjoin="2" position="9" opposite="2"/>
    <leaf n="10" mode="original" single="false" folio_number="20" conjoin="1" position="10" opposite="1"/>
  </quire>
  <quire n="3">
    <leaf n="1" mode="original" single="false" folio_number="21" conjoin="4" position="1" opposite="4"/>
    <leaf n="2" mode="original" single="false" folio_number="22" conjoin="3" position="2" opposite="3"/>
    <leaf n="3" mode="original" single="false" folio_number="23" conjoin="2" position="3" opposite="2"/>
    <leaf n="4" mode="original" single="false" folio_number="24" conjoin="1" position="4" opposite="1"/>
  </quire>
  <quire n="4">
    <leaf n="" conjoin="3" position="1" opposite="4"/>
    <leaf n="1" mode="original" single="false" folio_number="25" conjoin="2" position="2" opposite="3"/>
    <leaf n="2" mode="original" single="false" folio_number="26" conjoin="1" position="3" opposite="2"/>
    <leaf n="3" mode="original" single="true" folio_number="27" conjoin="" position="4" opposite="1"/>
  </quire>
  <quire n="5">
    <leaf n="1" mode="original" single="false" folio_number="28" conjoin="10" position="1" opposite="10"/>
    <leaf n="2" mode="original" single="false" folio_number="29" conjoin="9" position="2" opposite="9"/>
    <leaf n="3" mode="original" single="false" folio_number="30" conjoin="8" position="3" opposite="8"/>
    <leaf n="4" mode="original" single="false" folio_number="31" conjoin="7" position="4" opposite="7"/>
    <leaf n="5" mode="original" single="false" folio_number="32" conjoin="6" position="5" opposite="6"/>
    <leaf n="6" mode="original" single="false" folio_number="33" conjoin="5" position="6" opposite="5"/>
    <leaf n="7" mode="original" single="false" folio_number="34" conjoin="4" position="7" opposite="4"/>
    <leaf n="8" mode="original" single="false" folio_number="35" conjoin="3" position="8" opposite="3"/>
    <leaf n="9" mode="original" single="false" folio_number="36" conjoin="2" position="9" opposite="2"/>
    <leaf n="10" mode="original" single="false" folio_number="37" conjoin="1" position="10" opposite="1"/>
  </quire>
  <quire n="6">
    <leaf n="1" mode="original" single="false" folio_number="38" conjoin="10" position="1" opposite="10"/>
    <leaf n="2" mode="original" single="false" folio_number="39" conjoin="9" position="2" opposite="9"/>
    <leaf n="3" mode="original" single="false" folio_number="40" conjoin="8" position="3" opposite="8"/>
    <leaf n="4" mode="original" single="false" folio_number="41" conjoin="7" position="4" opposite="7"/>
    <leaf n="5" mode="original" single="false" folio_number="42" conjoin="6" position="5" opposite="6"/>
    <leaf n="6" mode="original" single="false" folio_number="43" conjoin="5" position="6" opposite="5"/>
    <leaf n="7" mode="original" single="false" folio_number="44" conjoin="4" position="7" opposite="4"/>
    <leaf n="8" mode="original" single="false" folio_number="45" conjoin="3" position="8" opposite="3"/>
    <leaf n="9" mode="original" single="false" folio_number="46" conjoin="2" position="9" opposite="2"/>
    <leaf n="10" mode="original" single="false" folio_number="47" conjoin="1" position="10" opposite="1"/>
  </quire>
  <quire n="7">
    <leaf n="1" mode="original" single="false" folio_number="48" conjoin="10" position="1" opposite="10"/>
    <leaf n="2" mode="original" single="false" folio_number="49" conjoin="9" position="2" opposite="9"/>
    <leaf n="3" mode="original" single="false" folio_number="50" conjoin="8" position="3" opposite="8"/>
    <leaf n="4" mode="original" single="false" folio_number="51" conjoin="7" position="4" opposite="7"/>
    <leaf n="5" mode="original" single="false" folio_number="52" conjoin="6" position="5" opposite="6"/>
    <leaf n="6" mode="original" single="false" folio_number="53" conjoin="5" position="6" opposite="5"/>
    <leaf n="7" mode="original" single="false" folio_number="54" conjoin="4" position="7" opposite="4"/>
    <leaf n="8" mode="original" single="false" folio_number="55" conjoin="3" position="8" opposite="3"/>
    <leaf n="9" mode="original" single="false" folio_number="56" conjoin="2" position="9" opposite="2"/>
    <leaf n="10" mode="original" single="false" folio_number="57" conjoin="1" position="10" opposite="1"/>
  </quire>
  <quire n="8">
    <leaf n="1" mode="original" single="false" folio_number="58" conjoin="10" position="1" opposite="10"/>
    <leaf n="2" mode="original" single="false" folio_number="59" conjoin="9" position="2" opposite="9"/>
    <leaf n="3" mode="original" single="false" folio_number="60" conjoin="8" position="3" opposite="8"/>
    <leaf n="4" mode="original" single="false" folio_number="61" conjoin="7" position="4" opposite="7"/>
    <leaf n="5" mode="original" single="false" folio_number="62" conjoin="6" position="5" opposite="6"/>
    <leaf n="6" mode="original" single="false" folio_number="63" conjoin="5" position="6" opposite="5"/>
    <leaf n="7" mode="original" single="false" folio_number="64" conjoin="4" position="7" opposite="4"/>
    <leaf n="8" mode="original" single="false" folio_number="65" conjoin="3" position="8" opposite="3"/>
    <leaf n="9" mode="original" single="false" folio_number="66" conjoin="2" position="9" opposite="2"/>
    <leaf n="10" mode="original" single="false" folio_number="67" conjoin="1" position="10" opposite="1"/>
  </quire>
  <quire n="9">
    <leaf n="1" mode="original" single="false" folio_number="68" conjoin="10" position="1" opposite="10"/>
    <leaf n="2" mode="original" single="false" folio_number="69" conjoin="9" position="2" opposite="9"/>
    <leaf n="3" mode="original" single="false" folio_number="70" conjoin="8" position="3" opposite="8"/>
    <leaf n="4" mode="original" single="false" folio_number="71" conjoin="7" position="4" opposite="7"/>
    <leaf n="5" mode="original" single="false" folio_number="72" conjoin="6" position="5" opposite="6"/>
    <leaf n="6" mode="original" single="false" folio_number="73" conjoin="5" position="6" opposite="5"/>
    <leaf n="7" mode="original" single="false" folio_number="74" conjoin="4" position="7" opposite="4"/>
    <leaf n="8" mode="original" single="false" folio_number="75" conjoin="3" position="8" opposite="3"/>
    <leaf n="9" mode="original" single="false" folio_number="76" conjoin="2" position="9" opposite="2"/>
    <leaf n="10" mode="original" single="false" folio_number="77" conjoin="1" position="10" opposite="1"/>
  </quire>
  <quire n="10">
    <leaf n="1" mode="original" single="false" folio_number="78" conjoin="10" position="1" opposite="10"/>
    <leaf n="2" mode="original" single="false" folio_number="79" conjoin="9" position="2" opposite="9"/>
    <leaf n="3" mode="original" single="false" folio_number="80" conjoin="8" position="3" opposite="8"/>
    <leaf n="4" mode="original" single="false" folio_number="81" conjoin="7" position="4" opposite="7"/>
    <leaf n="5" mode="original" single="false" folio_number="82" conjoin="6" position="5" opposite="6"/>
    <leaf n="6" mode="original" single="false" folio_number="83" conjoin="5" position="6" opposite="5"/>
    <leaf n="7" mode="original" single="false" folio_number="84" conjoin="4" position="7" opposite="4"/>
    <leaf n="8" mode="original" single="false" folio_number="85" conjoin="3" position="8" opposite="3"/>
    <leaf n="9" mode="original" single="false" folio_number="86" conjoin="2" position="9" opposite="2"/>
    <leaf n="10" mode="original" single="false" folio_number="87" conjoin="1" position="10" opposite="1"/>
  </quire>
  <quire n="11">
    <leaf n="1" mode="original" single="false" folio_number="88" conjoin="10" position="1" opposite="10"/>
    <leaf n="2" mode="original" single="false" folio_number="89" conjoin="9" position="2" opposite="9"/>
    <leaf n="3" mode="original" single="false" folio_number="90" conjoin="8" position="3" opposite="8"/>
    <leaf n="4" mode="original" single="false" folio_number="91" conjoin="7" position="4" opposite="7"/>
    <leaf n="5" mode="original" single="false" folio_number="92" conjoin="6" position="5" opposite="6"/>
    <leaf n="6" mode="original" single="false" folio_number="93" conjoin="5" position="6" opposite="5"/>
    <leaf n="7" mode="original" single="false" folio_number="94" conjoin="4" position="7" opposite="4"/>
    <leaf n="8" mode="original" single="false" folio_number="95" conjoin="3" position="8" opposite="3"/>
    <leaf n="9" mode="original" single="false" folio_number="96" conjoin="2" position="9" opposite="2"/>
    <leaf n="10" mode="original" single="false" folio_number="97" conjoin="1" position="10" opposite="1"/>
  </quire>
  <quire n="12">
    <leaf n="1" mode="original" single="false" folio_number="98" conjoin="10" position="1" opposite="10"/>
    <leaf n="2" mode="original" single="false" folio_number="99" conjoin="9" position="2" opposite="9"/>
    <leaf n="3" mode="original" single="false" folio_number="100" conjoin="8" position="3" opposite="8"/>
    <leaf n="4" mode="original" single="false" folio_number="101" conjoin="7" position="4" opposite="7"/>
    <leaf n="5" mode="original" single="false" folio_number="102" conjoin="6" position="5" opposite="6"/>
    <leaf n="6" mode="original" single="false" folio_number="103" conjoin="5" position="6" opposite="5"/>
    <leaf n="7" mode="original" single="false" folio_number="104" conjoin="4" position="7" opposite="4"/>
    <leaf n="8" mode="original" single="false" folio_number="105" conjoin="3" position="8" opposite="3"/>
    <leaf n="9" mode="original" single="false" folio_number="106" conjoin="2" position="9" opposite="2"/>
    <leaf n="10" mode="original" single="false" folio_number="107" conjoin="1" position="10" opposite="1"/>
  </quire>
  <quire n="13">
    <leaf n="1" mode="original" single="false" folio_number="108" conjoin="10" position="1" opposite="10"/>
    <leaf n="2" mode="original" single="false" folio_number="109" conjoin="9" position="2" opposite="9"/>
    <leaf n="3" mode="original" single="false" folio_number="110" conjoin="8" position="3" opposite="8"/>
    <leaf n="4" mode="original" single="false" folio_number="111" conjoin="7" position="4" opposite="7"/>
    <leaf n="5" mode="original" single="false" folio_number="112" conjoin="6" position="5" opposite="6"/>
    <leaf n="6" mode="original" single="false" folio_number="113" conjoin="5" position="6" opposite="5"/>
    <leaf n="7" mode="original" single="false" folio_number="114" conjoin="4" position="7" opposite="4"/>
    <leaf n="8" mode="original" single="false" folio_number="115" conjoin="3" position="8" opposite="3"/>
    <leaf n="9" mode="original" single="false" folio_number="116" conjoin="2" position="9" opposite="2"/>
    <leaf n="10" mode="original" single="false" folio_number="117" conjoin="1" position="10" opposite="1"/>
  </quire>
  <quire n="14">
    <leaf n="1" mode="original" single="false" folio_number="118" conjoin="10" position="1" opposite="10"/>
    <leaf n="2" mode="original" single="false" folio_number="119" conjoin="9" position="2" opposite="9"/>
    <leaf n="3" mode="original" single="false" folio_number="120" conjoin="8" position="3" opposite="8"/>
    <leaf n="4" mode="original" single="false" folio_number="121" conjoin="7" position="4" opposite="7"/>
    <leaf n="5" mode="original" single="false" folio_number="122" conjoin="6" position="5" opposite="6"/>
    <leaf n="6" mode="original" single="false" folio_number="123" conjoin="5" position="6" opposite="5"/>
    <leaf n="7" mode="original" single="false" folio_number="124" conjoin="4" position="7" opposite="4"/>
    <leaf n="8" mode="original" single="false" folio_number="125" conjoin="3" position="8" opposite="3"/>
    <leaf n="9" mode="original" single="false" folio_number="126" conjoin="2" position="9" opposite="2"/>
    <leaf n="10" mode="original" single="false" folio_number="127" conjoin="1" position="10" opposite="1"/>
  </quire>
  <quire n="15">
    <leaf n="1" mode="original" single="false" folio_number="128" conjoin="10" position="1" opposite="10"/>
    <leaf n="2" mode="original" single="false" folio_number="129" conjoin="9" position="2" opposite="9"/>
    <leaf n="3" mode="original" single="false" folio_number="130" conjoin="8" position="3" opposite="8"/>
    <leaf n="4" mode="original" single="false" folio_number="131" conjoin="7" position="4" opposite="7"/>
    <leaf n="5" mode="original" single="false" folio_number="132" conjoin="6" position="5" opposite="6"/>
    <leaf n="6" mode="original" single="false" folio_number="133" conjoin="5" position="6" opposite="5"/>
    <leaf n="7" mode="original" single="false" folio_number="134" conjoin="4" position="7" opposite="4"/>
    <leaf n="8" mode="original" single="false" folio_number="135" conjoin="3" position="8" opposite="3"/>
    <leaf n="9" mode="original" single="false" folio_number="136" conjoin="2" position="9" opposite="2"/>
    <leaf n="10" mode="original" single="false" folio_number="137" conjoin="1" position="10" opposite="1"/>
  </quire>
  <quire n="16">
    <leaf n="1" mode="original" single="false" folio_number="138" conjoin="10" position="1" opposite="10"/>
    <leaf n="2" mode="original" single="false" folio_number="139" conjoin="9" position="2" opposite="9"/>
    <leaf n="3" mode="original" single="false" folio_number="140" conjoin="8" position="3" opposite="8"/>
    <leaf n="4" mode="original" single="false" folio_number="141" conjoin="7" position="4" opposite="7"/>
    <leaf n="5" mode="original" single="false" folio_number="142" conjoin="6" position="5" opposite="6"/>
    <leaf n="6" mode="original" single="false" folio_number="143" conjoin="5" position="6" opposite="5"/>
    <leaf n="7" mode="original" single="false" folio_number="144" conjoin="4" position="7" opposite="4"/>
    <leaf n="8" mode="original" single="false" folio_number="145" conjoin="3" position="8" opposite="3"/>
    <leaf n="9" mode="original" single="false" folio_number="146" conjoin="2" position="9" opposite="2"/>
    <leaf n="10" mode="original" single="false" folio_number="147" conjoin="1" position="10" opposite="1"/>
  </quire>
  <quire n="17">
    <leaf n="1" mode="original" single="false" folio_number="148" conjoin="10" position="1" opposite="10"/>
    <leaf n="2" mode="original" single="false" folio_number="149" conjoin="9" position="2" opposite="9"/>
    <leaf n="3" mode="original" single="false" folio_number="150" conjoin="8" position="3" opposite="8"/>
    <leaf n="4" mode="original" single="false" folio_number="151" conjoin="7" position="4" opposite="7"/>
    <leaf n="5" mode="original" single="false" folio_number="152" conjoin="6" position="5" opposite="6"/>
    <leaf n="6" mode="original" single="false" folio_number="153" conjoin="5" position="6" opposite="5"/>
    <leaf n="7" mode="original" single="false" folio_number="154" conjoin="4" position="7" opposite="4"/>
    <leaf n="8" mode="original" single="false" folio_number="155" conjoin="3" position="8" opposite="3"/>
    <leaf n="9" mode="original" single="false" folio_number="156" conjoin="2" position="9" opposite="2"/>
    <leaf n="10" mode="original" single="false" folio_number="157" conjoin="1" position="10" opposite="1"/>
  </quire>
  <quire n="18">
    <leaf n="1" mode="original" single="false" folio_number="158" conjoin="10" position="1" opposite="10"/>
    <leaf n="2" mode="original" single="false" folio_number="159" conjoin="9" position="2" opposite="9"/>
    <leaf n="3" mode="original" single="false" folio_number="160" conjoin="8" position="3" opposite="8"/>
    <leaf n="4" mode="original" single="false" folio_number="161" conjoin="7" position="4" opposite="7"/>
    <leaf n="5" mode="original" single="false" folio_number="162" conjoin="6" position="5" opposite="6"/>
    <leaf n="6" mode="original" single="false" folio_number="163" conjoin="5" position="6" opposite="5"/>
    <leaf n="7" mode="original" single="false" folio_number="164" conjoin="4" position="7" opposite="4"/>
    <leaf n="8" mode="original" single="false" folio_number="165" conjoin="3" position="8" opposite="3"/>
    <leaf n="9" mode="original" single="false" folio_number="166" conjoin="2" position="9" opposite="2"/>
    <leaf n="10" mode="original" single="false" folio_number="167" conjoin="1" position="10" opposite="1"/>
  </quire>
  <quire n="19">
    <leaf n="1" mode="original" single="false" folio_number="168" conjoin="10" position="1" opposite="10"/>
    <leaf n="2" mode="original" single="false" folio_number="169" conjoin="9" position="2" opposite="9"/>
    <leaf n="3" mode="original" single="false" folio_number="170" conjoin="8" position="3" opposite="8"/>
    <leaf n="4" mode="original" single="false" folio_number="171" conjoin="7" position="4" opposite="7"/>
    <leaf n="5" mode="original" single="false" folio_number="172" conjoin="6" position="5" opposite="6"/>
    <leaf n="6" mode="original" single="false" folio_number="173" conjoin="5" position="6" opposite="5"/>
    <leaf n="7" mode="original" single="false" folio_number="174" conjoin="4" position="7" opposite="4"/>
    <leaf n="8" mode="original" single="false" folio_number="175" conjoin="3" position="8" opposite="3"/>
    <leaf n="9" mode="original" single="false" folio_number="176" conjoin="2" position="9" opposite="2"/>
    <leaf n="10" mode="original" single="false" folio_number="177" conjoin="1" position="10" opposite="1"/>
  </quire>
  <quire n="20">
    <leaf n="1" mode="original" single="false" folio_number="178" conjoin="10" position="1" opposite="10"/>
    <leaf n="2" mode="original" single="false" folio_number="179" conjoin="9" position="2" opposite="9"/>
    <leaf n="3" mode="original" single="false" folio_number="180" conjoin="8" position="3" opposite="8"/>
    <leaf n="4" mode="original" single="false" folio_number="181" conjoin="7" position="4" opposite="7"/>
    <leaf n="5" mode="original" single="false" folio_number="182" conjoin="6" position="5" opposite="6"/>
    <leaf n="6" mode="original" single="false" folio_number="183" conjoin="5" position="6" opposite="5"/>
    <leaf n="7" mode="original" single="false" folio_number="184" conjoin="4" position="7" opposite="4"/>
    <leaf n="8" mode="original" single="false" folio_number="185" conjoin="3" position="8" opposite="3"/>
    <leaf n="9" mode="original" single="false" folio_number="186" conjoin="2" position="9" opposite="2"/>
    <leaf n="10" mode="original" single="false" folio_number="187" conjoin="1" position="10" opposite="1"/>
  </quire>
  <quire n="21">
    <leaf n="1" mode="original" single="false" folio_number="188" conjoin="10" position="1" opposite="10"/>
    <leaf n="2" mode="original" single="false" folio_number="189" conjoin="9" position="2" opposite="9"/>
    <leaf n="3" mode="original" single="false" folio_number="190" conjoin="8" position="3" opposite="8"/>
    <leaf n="4" mode="original" single="false" folio_number="191" conjoin="7" position="4" opposite="7"/>
    <leaf n="5" mode="original" single="false" folio_number="192" conjoin="6" position="5" opposite="6"/>
    <leaf n="6" mode="original" single="false" folio_number="193" conjoin="5" position="6" opposite="5"/>
    <leaf n="7" mode="original" single="false" folio_number="194" conjoin="4" position="7" opposite="4"/>
    <leaf n="8" mode="original" single="false" folio_number="195" conjoin="3" position="8" opposite="3"/>
    <leaf n="9" mode="original" single="false" folio_number="196" conjoin="2" position="9" opposite="2"/>
    <leaf n="10" mode="original" single="false" folio_number="197" conjoin="1" position="10" opposite="1"/>
  </quire>
  <quire n="22">
    <leaf n="1" mode="original" single="false" folio_number="198" conjoin="10" position="1" opposite="10"/>
    <leaf n="2" mode="original" single="false" folio_number="199" conjoin="9" position="2" opposite="9"/>
    <leaf n="3" mode="original" single="false" folio_number="200" conjoin="8" position="3" opposite="8"/>
    <leaf n="4" mode="original" single="false" folio_number="201" conjoin="7" position="4" opposite="7"/>
    <leaf n="5" mode="original" single="false" folio_number="202" conjoin="6" position="5" opposite="6"/>
    <leaf n="6" mode="original" single="false" folio_number="203" conjoin="5" position="6" opposite="5"/>
    <leaf n="7" mode="original" single="false" folio_number="204" conjoin="4" position="7" opposite="4"/>
    <leaf n="8" mode="original" single="false" folio_number="205" conjoin="3" position="8" opposite="3"/>
    <leaf n="9" mode="original" single="false" folio_number="206" conjoin="2" position="9" opposite="2"/>
    <leaf n="10" mode="original" single="false" folio_number="207" conjoin="1" position="10" opposite="1"/>
  </quire>
  <quire n="23">
    <leaf n="1" mode="original" single="false" folio_number="208" conjoin="10" position="1" opposite="10"/>
    <leaf n="2" mode="original" single="false" folio_number="209" conjoin="9" position="2" opposite="9"/>
    <leaf n="3" mode="original" single="false" folio_number="210" conjoin="8" position="3" opposite="8"/>
    <leaf n="4" mode="original" single="false" folio_number="211" conjoin="7" position="4" opposite="7"/>
    <leaf n="5" mode="original" single="false" folio_number="212" conjoin="6" position="5" opposite="6"/>
    <leaf n="6" mode="original" single="false" folio_number="213" conjoin="5" position="6" opposite="5"/>
    <leaf n="7" mode="original" single="false" folio_number="214" conjoin="4" position="7" opposite="4"/>
    <leaf n="8" mode="original" single="false" folio_number="215" conjoin="3" position="8" opposite="3"/>
    <leaf n="9" mode="original" single="false" folio_number="216" conjoin="2" position="9" opposite="2"/>
    <leaf n="10" mode="original" single="false" folio_number="217" conjoin="1" position="10" opposite="1"/>
  </quire>
  <quire n="24">
    <leaf n="1" mode="original" single="false" folio_number="218" conjoin="10" position="1" opposite="10"/>
    <leaf n="2" mode="original" single="false" folio_number="219" conjoin="9" position="2" opposite="9"/>
    <leaf n="3" mode="original" single="false" folio_number="220" conjoin="8" position="3" opposite="8"/>
    <leaf n="4" mode="original" single="false" folio_number="221" conjoin="7" position="4" opposite="7"/>
    <leaf n="5" mode="original" single="false" folio_number="222" conjoin="6" position="5" opposite="6"/>
    <leaf n="6" mode="original" single="false" folio_number="223" conjoin="5" position="6" opposite="5"/>
    <leaf n="7" mode="original" single="false" folio_number="224" conjoin="4" position="7" opposite="4"/>
    <leaf n="8" mode="original" single="false" folio_number="225" conjoin="3" position="8" opposite="3"/>
    <leaf n="9" mode="original" single="false" folio_number="226" conjoin="2" position="9" opposite="2"/>
    <leaf n="10" mode="original" single="false" folio_number="227" conjoin="1" position="10" opposite="1"/>
  </quire>
  <quire n="25">
    <leaf n="1" mode="original" single="false" folio_number="228" conjoin="10" position="1" opposite="10"/>
    <leaf n="2" mode="original" single="false" folio_number="229" conjoin="9" position="2" opposite="9"/>
    <leaf n="3" mode="original" single="false" folio_number="230" conjoin="8" position="3" opposite="8"/>
    <leaf n="4" mode="original" single="false" folio_number="231" conjoin="7" position="4" opposite="7"/>
    <leaf n="5" mode="original" single="false" folio_number="232" conjoin="6" position="5" opposite="6"/>
    <leaf n="6" mode="original" single="false" folio_number="233" conjoin="5" position="6" opposite="5"/>
    <leaf n="7" mode="original" single="false" folio_number="234" conjoin="4" position="7" opposite="4"/>
    <leaf n="8" mode="original" single="false" folio_number="235" conjoin="3" position="8" opposite="3"/>
    <leaf n="9" mode="original" single="false" folio_number="236" conjoin="2" position="9" opposite="2"/>
    <leaf n="10" mode="original" single="false" folio_number="237" conjoin="1" position="10" opposite="1"/>
  </quire>
  <quire n="26">
    <leaf n="1" mode="original" single="false" folio_number="238" conjoin="10" position="1" opposite="10"/>
    <leaf n="2" mode="original" single="false" folio_number="239" conjoin="9" position="2" opposite="9"/>
    <leaf n="3" mode="original" single="false" folio_number="240" conjoin="8" position="3" opposite="8"/>
    <leaf n="4" mode="original" single="false" folio_number="241" conjoin="7" position="4" opposite="7"/>
    <leaf n="5" mode="original" single="false" folio_number="242" conjoin="6" position="5" opposite="6"/>
    <leaf n="6" mode="original" single="false" folio_number="243" conjoin="5" position="6" opposite="5"/>
    <leaf n="7" mode="original" single="false" folio_number="244" conjoin="4" position="7" opposite="4"/>
    <leaf n="8" mode="original" single="false" folio_number="245" conjoin="3" position="8" opposite="3"/>
    <leaf n="9" mode="original" single="false" folio_number="246" conjoin="2" position="9" opposite="2"/>
    <leaf n="10" mode="original" single="false" folio_number="247" conjoin="1" position="10" opposite="1"/>
  </quire>
  <quire n="27">
    <leaf n="1" mode="original" single="false" folio_number="248" conjoin="10" position="1" opposite="10"/>
    <leaf n="2" mode="original" single="false" folio_number="249" conjoin="9" position="2" opposite="9"/>
    <leaf n="3" mode="original" single="false" folio_number="250" conjoin="8" position="3" opposite="8"/>
    <leaf n="4" mode="original" single="false" folio_number="251" conjoin="7" position="4" opposite="7"/>
    <leaf n="5" mode="original" single="false" folio_number="252" conjoin="6" position="5" opposite="6"/>
    <leaf n="6" mode="original" single="false" folio_number="253" conjoin="5" position="6" opposite="5"/>
    <leaf n="7" mode="original" single="false" folio_number="254" conjoin="4" position="7" opposite="4"/>
    <leaf n="8" mode="original" single="false" folio_number="255" conjoin="3" position="8" opposite="3"/>
    <leaf n="9" mode="original" single="false" folio_number="256" conjoin="2" position="9" opposite="2"/>
    <leaf n="10" mode="original" single="false" folio_number="257" conjoin="1" position="10" opposite="1"/>
  </quire>
  <quire n="28">
    <leaf n="1" mode="original" single="false" folio_number="258" conjoin="10" position="1" opposite="10"/>
    <leaf n="2" mode="original" single="false" folio_number="259" conjoin="9" position="2" opposite="9"/>
    <leaf n="3" mode="original" single="false" folio_number="260" conjoin="8" position="3" opposite="8"/>
    <leaf n="4" mode="original" single="false" folio_number="261" conjoin="7" position="4" opposite="7"/>
    <leaf n="5" mode="original" single="false" folio_number="262" conjoin="6" position="5" opposite="6"/>
    <leaf n="6" mode="original" single="false" folio_number="263" conjoin="5" position="6" opposite="5"/>
    <leaf n="7" mode="original" single="false" folio_number="264" conjoin="4" position="7" opposite="4"/>
    <leaf n="8" mode="original" single="false" folio_number="265" conjoin="3" position="8" opposite="3"/>
    <leaf n="9" mode="original" single="false" folio_number="266" conjoin="2" position="9" opposite="2"/>
    <leaf n="10" mode="original" single="false" folio_number="267" conjoin="1" position="10" opposite="1"/>
  </quire>
  <quire n="29">
    <leaf n="1" mode="original" single="false" folio_number="268" conjoin="10" position="1" opposite="10"/>
    <leaf n="2" mode="original" single="false" folio_number="269" conjoin="9" position="2" opposite="9"/>
    <leaf n="3" mode="original" single="false" folio_number="270" conjoin="8" position="3" opposite="8"/>
    <leaf n="4" mode="original" single="false" folio_number="271" conjoin="7" position="4" opposite="7"/>
    <leaf n="5" mode="original" single="false" folio_number="272" conjoin="6" position="5" opposite="6"/>
    <leaf n="6" mode="original" single="false" folio_number="273" conjoin="5" position="6" opposite="5"/>
    <leaf n="7" mode="original" single="false" folio_number="274" conjoin="4" position="7" opposite="4"/>
    <leaf n="8" mode="original" single="false" folio_number="275" conjoin="3" position="8" opposite="3"/>
    <leaf n="9" mode="original" single="false" folio_number="276" conjoin="2" position="9" opposite="2"/>
    <leaf n="10" mode="original" single="false" folio_number="277" conjoin="1" position="10" opposite="1"/>
  </quire>
  <quire n="30">
    <leaf n="1" mode="original" single="false" folio_number="278" conjoin="10" position="1" opposite="10"/>
    <leaf n="2" mode="original" single="false" folio_number="279" conjoin="9" position="2" opposite="9"/>
    <leaf n="3" mode="original" single="false" folio_number="280" conjoin="8" position="3" opposite="8"/>
    <leaf n="4" mode="original" single="false" folio_number="281" conjoin="7" position="4" opposite="7"/>
    <leaf n="5" mode="original" single="false" folio_number="282" conjoin="6" position="5" opposite="6"/>
    <leaf n="6" mode="original" single="false" folio_number="283" conjoin="5" position="6" opposite="5"/>
    <leaf n="7" mode="original" single="false" folio_number="284" conjoin="4" position="7" opposite="4"/>
    <leaf n="8" mode="original" single="false" folio_number="285" conjoin="3" position="8" opposite="3"/>
    <leaf n="9" mode="original" single="false" folio_number="286" conjoin="2" position="9" opposite="2"/>
    <leaf n="10" mode="original" single="false" folio_number="287" conjoin="1" position="10" opposite="1"/>
  </quire>
  <quire n="31">
    <leaf n="1" mode="original" single="false" folio_number="288" conjoin="10" position="1" opposite="10"/>
    <leaf n="2" mode="original" single="false" folio_number="289" conjoin="9" position="2" opposite="9"/>
    <leaf n="3" mode="original" single="false" folio_number="290" conjoin="8" position="3" opposite="8"/>
    <leaf n="4" mode="original" single="false" folio_number="291" conjoin="7" position="4" opposite="7"/>
    <leaf n="5" mode="original" single="false" folio_number="292" conjoin="6" position="5" opposite="6"/>
    <leaf n="6" mode="original" single="false" folio_number="293" conjoin="5" position="6" opposite="5"/>
    <leaf n="7" mode="original" single="false" folio_number="294" conjoin="4" position="7" opposite="4"/>
    <leaf n="8" mode="original" single="false" folio_number="295" conjoin="3" position="8" opposite="3"/>
    <leaf n="9" mode="original" single="false" folio_number="296" conjoin="2" position="9" opposite="2"/>
    <leaf n="10" mode="original" single="false" folio_number="297" conjoin="1" position="10" opposite="1"/>
  </quire>
  <quire n="32">
    <leaf n="1" mode="original" single="false" folio_number="298" conjoin="10" position="1" opposite="10"/>
    <leaf n="2" mode="original" single="false" folio_number="299" conjoin="9" position="2" opposite="9"/>
    <leaf n="3" mode="original" single="false" folio_number="300" conjoin="8" position="3" opposite="8"/>
    <leaf n="4" mode="original" single="false" folio_number="301" conjoin="7" position="4" opposite="7"/>
    <leaf n="5" mode="original" single="false" folio_number="302" conjoin="6" position="5" opposite="6"/>
    <leaf n="6" mode="original" single="false" folio_number="303" conjoin="5" position="6" opposite="5"/>
    <leaf n="7" mode="original" single="false" folio_number="304" conjoin="4" position="7" opposite="4"/>
    <leaf n="8" mode="original" single="false" folio_number="305" conjoin="3" position="8" opposite="3"/>
    <leaf n="9" mode="original" single="false" folio_number="306" conjoin="2" position="9" opposite="2"/>
    <leaf n="10" mode="original" single="false" folio_number="307" conjoin="1" position="10" opposite="1"/>
  </quire>
  <quire n="33">
    <leaf n="1" mode="original" single="false" folio_number="308" conjoin="10" position="1" opposite="10"/>
    <leaf n="2" mode="original" single="false" folio_number="309" conjoin="9" position="2" opposite="9"/>
    <leaf n="3" mode="original" single="false" folio_number="310" conjoin="8" position="3" opposite="8"/>
    <leaf n="4" mode="original" single="false" folio_number="311" conjoin="7" position="4" opposite="7"/>
    <leaf n="5" mode="original" single="false" folio_number="312" conjoin="6" position="5" opposite="6"/>
    <leaf n="6" mode="original" single="false" folio_number="313" conjoin="5" position="6" opposite="5"/>
    <leaf n="7" mode="original" single="false" folio_number="314" conjoin="4" position="7" opposite="4"/>
    <leaf n="8" mode="original" single="false" folio_number="315" conjoin="3" position="8" opposite="3"/>
    <leaf n="9" mode="original" single="false" folio_number="316" conjoin="2" position="9" opposite="2"/>
    <leaf n="10" mode="original" single="false" folio_number="317" conjoin="1" position="10" opposite="1"/>
  </quire>
  <quire n="34">
    <leaf n="1" mode="original" single="false" folio_number="318" conjoin="10" position="1" opposite="10"/>
    <leaf n="2" mode="original" single="false" folio_number="319" conjoin="9" position="2" opposite="9"/>
    <leaf n="3" mode="original" single="false" folio_number="320" conjoin="8" position="3" opposite="8"/>
    <leaf n="4" mode="original" single="false" folio_number="321" conjoin="7" position="4" opposite="7"/>
    <leaf n="5" mode="original" single="false" folio_number="322" conjoin="6" position="5" opposite="6"/>
    <leaf n="6" mode="original" single="false" folio_number="323" conjoin="5" position="6" opposite="5"/>
    <leaf n="7" mode="original" single="false" folio_number="324" conjoin="4" position="7" opposite="4"/>
    <leaf n="8" mode="original" single="false" folio_number="325" conjoin="3" position="8" opposite="3"/>
    <leaf n="9" mode="original" single="false" folio_number="326" conjoin="2" position="9" opposite="2"/>
    <leaf n="10" mode="original" single="false" folio_number="327" conjoin="1" position="10" opposite="1"/>
  </quire>
  <quire n="35">
    <leaf n="1" mode="original" single="false" folio_number="328" conjoin="10" position="1" opposite="10"/>
    <leaf n="2" mode="original" single="false" folio_number="329" conjoin="9" position="2" opposite="9"/>
    <leaf n="3" mode="original" single="false" folio_number="330" conjoin="8" position="3" opposite="8"/>
    <leaf n="4" mode="original" single="false" folio_number="331" conjoin="7" position="4" opposite="7"/>
    <leaf n="5" mode="original" single="false" folio_number="332" conjoin="6" position="5" opposite="6"/>
    <leaf n="6" mode="original" single="false" folio_number="333" conjoin="5" position="6" opposite="5"/>
    <leaf n="7" mode="original" single="false" folio_number="334" conjoin="4" position="7" opposite="4"/>
    <leaf n="8" mode="original" single="false" folio_number="335" conjoin="3" position="8" opposite="3"/>
    <leaf n="9" mode="original" single="false" folio_number="336" conjoin="2" position="9" opposite="2"/>
    <leaf n="10" mode="original" single="false" folio_number="337" conjoin="1" position="10" opposite="1"/>
  </quire>
  <quire n="36">
    <leaf n="1" mode="original" single="false" folio_number="338" conjoin="10" position="1" opposite="10"/>
    <leaf n="2" mode="original" single="false" folio_number="339" conjoin="9" position="2" opposite="9"/>
    <leaf n="3" mode="original" single="false" folio_number="340" conjoin="8" position="3" opposite="8"/>
    <leaf n="4" mode="original" single="false" folio_number="341" conjoin="7" position="4" opposite="7"/>
    <leaf n="5" mode="original" single="false" folio_number="342" conjoin="6" position="5" opposite="6"/>
    <leaf n="6" mode="original" single="false" folio_number="343" conjoin="5" position="6" opposite="5"/>
    <leaf n="7" mode="original" single="false" folio_number="344" conjoin="4" position="7" opposite="4"/>
    <leaf n="8" mode="original" single="false" folio_number="345" conjoin="3" position="8" opposite="3"/>
    <leaf n="9" mode="original" single="false" folio_number="346" conjoin="2" position="9" opposite="2"/>
    <leaf n="10" mode="original" single="false" folio_number="347" conjoin="1" position="10" opposite="1"/>
  </quire>
  <quire n="37">
    <leaf n="1" mode="original" single="false" folio_number="348" conjoin="6" position="1" opposite="6"/>
    <leaf n="2" mode="original" single="false" folio_number="349" conjoin="5" position="2" opposite="5"/>
    <leaf n="3" mode="original" single="false" folio_number="350" conjoin="4" position="3" opposite="4"/>
    <leaf n="4" mode="original" single="false" folio_number="351" conjoin="3" position="4" opposite="3"/>
    <leaf n="5" mode="original" single="false" folio_number="352" conjoin="2" position="5" opposite="2"/>
    <leaf n="6" mode="original" single="false" folio_number="353" conjoin="1" position="6" opposite="1"/>
  </quire>
  <quire n="38">
    <leaf n="1" mode="original" single="false" folio_number="354" conjoin="10" position="1" opposite="10"/>
    <leaf n="2" mode="original" single="false" folio_number="355" conjoin="9" position="2" opposite="9"/>
    <leaf n="3" mode="original" single="false" folio_number="356" conjoin="8" position="3" opposite="8"/>
    <leaf n="4" mode="original" single="false" folio_number="357" conjoin="7" position="4" opposite="7"/>
    <leaf n="5" mode="original" single="false" folio_number="358" conjoin="6" position="5" opposite="6"/>
    <leaf n="6" mode="original" single="false" folio_number="359" conjoin="5" position="6" opposite="5"/>
    <leaf n="7" mode="original" single="false" folio_number="360" conjoin="4" position="7" opposite="4"/>
    <leaf n="8" mode="original" single="false" folio_number="361" conjoin="3" position="8" opposite="3"/>
    <leaf n="9" mode="original" single="false" folio_number="362" conjoin="2" position="9" opposite="2"/>
    <leaf n="10" mode="original" single="false" folio_number="363" conjoin="1" position="10" opposite="1"/>
  </quire>
  <quire n="39">
    <leaf n="1" mode="original" single="false" folio_number="364" conjoin="10" position="1" opposite="10"/>
    <leaf n="2" mode="original" single="false" folio_number="365" conjoin="9" position="2" opposite="9"/>
    <leaf n="3" mode="original" single="false" folio_number="366" conjoin="8" position="3" opposite="8"/>
    <leaf n="4" mode="original" single="false" folio_number="367" conjoin="7" position="4" opposite="7"/>
    <leaf n="5" mode="original" single="false" folio_number="368" conjoin="6" position="5" opposite="6"/>
    <leaf n="6" mode="original" single="false" folio_number="369" conjoin="5" position="6" opposite="5"/>
    <leaf n="7" mode="original" single="false" folio_number="370" conjoin="4" position="7" opposite="4"/>
    <leaf n="8" mode="original" single="false" folio_number="371" conjoin="3" position="8" opposite="3"/>
    <leaf n="9" mode="original" single="false" folio_number="372" conjoin="2" position="9" opposite="2"/>
    <leaf n="10" mode="original" single="false" folio_number="373" conjoin="1" position="10" opposite="1"/>
  </quire>
  <quire n="40">
    <leaf n="1" mode="original" single="false" folio_number="374" conjoin="10" position="1" opposite="10"/>
    <leaf n="2" mode="original" single="false" folio_number="375" conjoin="9" position="2" opposite="9"/>
    <leaf n="3" mode="original" single="false" folio_number="376" conjoin="8" position="3" opposite="8"/>
    <leaf n="4" mode="original" single="false" folio_number="377" conjoin="7" position="4" opposite="7"/>
    <leaf n="5" mode="original" single="false" folio_number="378" conjoin="6" position="5" opposite="6"/>
    <leaf n="6" mode="original" single="false" folio_number="379" conjoin="5" position="6" opposite="5"/>
    <leaf n="7" mode="original" single="false" folio_number="380" conjoin="4" position="7" opposite="4"/>
    <leaf n="8" mode="original" single="false" folio_number="381" conjoin="3" position="8" opposite="3"/>
    <leaf n="9" mode="original" single="false" folio_number="382" conjoin="2" position="9" opposite="2"/>
    <leaf n="10" mode="original" single="false" folio_number="383" conjoin="1" position="10" opposite="1"/>
  </quire>
  <quire n="41">
    <leaf n="1" mode="original" single="false" folio_number="384" conjoin="10" position="1" opposite="10"/>
    <leaf n="2" mode="original" single="false" folio_number="385" conjoin="9" position="2" opposite="9"/>
    <leaf n="3" mode="original" single="false" folio_number="386" conjoin="8" position="3" opposite="8"/>
    <leaf n="4" mode="original" single="false" folio_number="387" conjoin="7" position="4" opposite="7"/>
    <leaf n="5" mode="original" single="false" folio_number="388" conjoin="6" position="5" opposite="6"/>
    <leaf n="6" mode="original" single="false" folio_number="389" conjoin="5" position="6" opposite="5"/>
    <leaf n="7" mode="original" single="false" folio_number="390" conjoin="4" position="7" opposite="4"/>
    <leaf n="8" mode="original" single="false" folio_number="391" conjoin="3" position="8" opposite="3"/>
    <leaf n="9" mode="original" single="false" folio_number="392" conjoin="2" position="9" opposite="2"/>
    <leaf n="10" mode="original" single="false" folio_number="393" conjoin="1" position="10" opposite="1"/>
  </quire>
  <quire n="42">
    <leaf n="1" mode="original" single="false" folio_number="394" conjoin="10" position="1" opposite="10"/>
    <leaf n="2" mode="original" single="false" folio_number="395" conjoin="9" position="2" opposite="9"/>
    <leaf n="3" mode="original" single="false" folio_number="396" conjoin="8" position="3" opposite="8"/>
    <leaf n="4" mode="original" single="false" folio_number="397" conjoin="7" position="4" opposite="7"/>
    <leaf n="5" mode="original" single="false" folio_number="398" conjoin="6" position="5" opposite="6"/>
    <leaf n="6" mode="original" single="false" folio_number="399" conjoin="5" position="6" opposite="5"/>
    <leaf n="7" mode="original" single="false" folio_number="400" conjoin="4" position="7" opposite="4"/>
    <leaf n="8" mode="original" single="false" folio_number="401" conjoin="3" position="8" opposite="3"/>
    <leaf n="9" mode="original" single="false" folio_number="402" conjoin="2" position="9" opposite="2"/>
    <leaf n="10" mode="original" single="false" folio_number="403" conjoin="1" position="10" opposite="1"/>
  </quire>
  <quire n="43">
    <leaf n="1" mode="original" single="false" folio_number="404" conjoin="10" position="1" opposite="10"/>
    <leaf n="2" mode="original" single="false" folio_number="405" conjoin="9" position="2" opposite="9"/>
    <leaf n="3" mode="original" single="false" folio_number="406" conjoin="8" position="3" opposite="8"/>
    <leaf n="4" mode="original" single="false" folio_number="407" conjoin="7" position="4" opposite="7"/>
    <leaf n="5" mode="original" single="false" folio_number="408" conjoin="6" position="5" opposite="6"/>
    <leaf n="6" mode="original" single="false" folio_number="409" conjoin="5" position="6" opposite="5"/>
    <leaf n="7" mode="original" single="false" folio_number="410" conjoin="4" position="7" opposite="4"/>
    <leaf n="8" mode="original" single="false" folio_number="411" conjoin="3" position="8" opposite="3"/>
    <leaf n="9" mode="original" single="false" folio_number="412" conjoin="2" position="9" opposite="2"/>
    <leaf n="10" mode="original" single="false" folio_number="413" conjoin="1" position="10" opposite="1"/>
  </quire>
  <quire n="44">
    <leaf n="1" mode="original" single="false" folio_number="414" conjoin="10" position="1" opposite="10"/>
    <leaf n="2" mode="original" single="false" folio_number="415" conjoin="9" position="2" opposite="9"/>
    <leaf n="3" mode="original" single="false" folio_number="416" conjoin="8" position="3" opposite="8"/>
    <leaf n="4" mode="original" single="false" folio_number="417" conjoin="7" position="4" opposite="7"/>
    <leaf n="5" mode="original" single="false" folio_number="418" conjoin="6" position="5" opposite="6"/>
    <leaf n="6" mode="original" single="false" folio_number="419" conjoin="5" position="6" opposite="5"/>
    <leaf n="7" mode="original" single="false" folio_number="420" conjoin="4" position="7" opposite="4"/>
    <leaf n="8" mode="original" single="false" folio_number="421" conjoin="3" position="8" opposite="3"/>
    <leaf n="9" mode="original" single="false" folio_number="422" conjoin="2" position="9" opposite="2"/>
    <leaf n="10" mode="original" single="false" folio_number="423" conjoin="1" position="10" opposite="1"/>
  </quire>
  <quire n="45">
    <leaf n="1" mode="original" single="false" folio_number="424" conjoin="10" position="1" opposite="10"/>
    <leaf n="2" mode="original" single="false" folio_number="425" conjoin="9" position="2" opposite="9"/>
    <leaf n="3" mode="original" single="false" folio_number="426" conjoin="8" position="3" opposite="8"/>
    <leaf n="4" mode="original" single="false" folio_number="427" conjoin="7" position="4" opposite="7"/>
    <leaf n="5" mode="original" single="false" folio_number="428" conjoin="6" position="5" opposite="6"/>
    <leaf n="6" mode="original" single="false" folio_number="429" conjoin="5" position="6" opposite="5"/>
    <leaf n="7" mode="original" single="false" folio_number="430" conjoin="4" position="7" opposite="4"/>
    <leaf n="8" mode="original" single="false" folio_number="431" conjoin="3" position="8" opposite="3"/>
    <leaf n="9" mode="original" single="false" folio_number="432" conjoin="2" position="9" opposite="2"/>
    <leaf n="10" mode="original" single="false" folio_number="433" conjoin="1" position="10" opposite="1"/>
  </quire>
  <quire n="46">
    <leaf n="1" mode="original" single="false" folio_number="434" conjoin="10" position="1" opposite="10"/>
    <leaf n="2" mode="original" single="false" folio_number="435" conjoin="9" position="2" opposite="9"/>
    <leaf n="3" mode="original" single="false" folio_number="436" conjoin="8" position="3" opposite="8"/>
    <leaf n="4" mode="original" single="false" folio_number="437" conjoin="7" position="4" opposite="7"/>
    <leaf n="5" mode="original" single="false" folio_number="438" conjoin="6" position="5" opposite="6"/>
    <leaf n="6" mode="original" single="false" folio_number="439" conjoin="5" position="6" opposite="5"/>
    <leaf n="7" mode="original" single="false" folio_number="440" conjoin="4" position="7" opposite="4"/>
    <leaf n="8" mode="original" single="false" folio_number="441" conjoin="3" position="8" opposite="3"/>
    <leaf n="9" mode="original" single="false" folio_number="442" conjoin="2" position="9" opposite="2"/>
    <leaf n="10" mode="original" single="false" folio_number="443" conjoin="1" position="10" opposite="1"/>
  </quire>
  <quire n="47">
    <leaf n="1" mode="original" single="false" folio_number="444" conjoin="10" position="1" opposite="10"/>
    <leaf n="2" mode="original" single="false" folio_number="445" conjoin="9" position="2" opposite="9"/>
    <leaf n="3" mode="original" single="false" folio_number="446" conjoin="8" position="3" opposite="8"/>
    <leaf n="4" mode="original" single="false" folio_number="447" conjoin="7" position="4" opposite="7"/>
    <leaf n="5" mode="original" single="false" folio_number="448" conjoin="6" position="5" opposite="6"/>
    <leaf n="6" mode="original" single="false" folio_number="449" conjoin="5" position="6" opposite="5"/>
    <leaf n="7" mode="original" single="false" folio_number="450" conjoin="4" position="7" opposite="4"/>
    <leaf n="8" mode="original" single="false" folio_number="451" conjoin="3" position="8" opposite="3"/>
    <leaf n="9" mode="original" single="false" folio_number="452" conjoin="2" position="9" opposite="2"/>
    <leaf n="10" mode="original" single="false" folio_number="453" conjoin="1" position="10" opposite="1"/>
  </quire>
  <quire n="48">
    <leaf n="1" mode="original" single="false" folio_number="454" conjoin="10" position="1" opposite="10"/>
    <leaf n="2" mode="original" single="false" folio_number="455" conjoin="9" position="2" opposite="9"/>
    <leaf n="3" mode="original" single="false" folio_number="456" conjoin="8" position="3" opposite="8"/>
    <leaf n="4" mode="original" single="false" folio_number="457" conjoin="7" position="4" opposite="7"/>
    <leaf n="5" mode="original" single="false" folio_number="458" conjoin="6" position="5" opposite="6"/>
    <leaf n="6" mode="original" single="false" folio_number="459" conjoin="5" position="6" opposite="5"/>
    <leaf n="7" mode="original" single="false" folio_number="460" conjoin="4" position="7" opposite="4"/>
    <leaf n="8" mode="original" single="false" folio_number="461" conjoin="3" position="8" opposite="3"/>
    <leaf n="9" mode="original" single="false" folio_number="462" conjoin="2" position="9" opposite="2"/>
    <leaf n="10" mode="original" single="false" folio_number="463" conjoin="1" position="10" opposite="1"/>
  </quire>
  <quire n="49">
    <leaf n="1" mode="original" single="false" folio_number="464" conjoin="10" position="1" opposite="10"/>
    <leaf n="2" mode="original" single="false" folio_number="465" conjoin="9" position="2" opposite="9"/>
    <leaf n="3" mode="original" single="false" folio_number="466" conjoin="8" position="3" opposite="8"/>
    <leaf n="4" mode="original" single="false" folio_number="467" conjoin="7" position="4" opposite="7"/>
    <leaf n="5" mode="original" single="false" folio_number="468" conjoin="6" position="5" opposite="6"/>
    <leaf n="6" mode="original" single="false" folio_number="469" conjoin="5" position="6" opposite="5"/>
    <leaf n="7" mode="original" single="false" folio_number="470" conjoin="4" position="7" opposite="4"/>
    <leaf n="8" mode="original" single="false" folio_number="471" conjoin="3" position="8" opposite="3"/>
    <leaf n="9" mode="original" single="false" folio_number="472" conjoin="2" position="9" opposite="2"/>
    <leaf n="10" mode="original" single="false" folio_number="473" conjoin="1" position="10" opposite="1"/>
  </quire>
  <quire n="50">
    <leaf n="1" mode="original" single="false" folio_number="474" conjoin="8" position="1" opposite="8"/>
    <leaf n="2" mode="original" single="false" folio_number="475" conjoin="7" position="2" opposite="7"/>
    <leaf n="3" mode="original" single="false" folio_number="476" conjoin="6" position="3" opposite="6"/>
    <leaf n="4" mode="original" single="false" folio_number="477" conjoin="5" position="4" opposite="5"/>
    <leaf n="5" mode="original" single="false" folio_number="478" conjoin="4" position="5" opposite="4"/>
    <leaf n="6" mode="original" single="false" folio_number="479" conjoin="3" position="6" opposite="3"/>
    <leaf n="7" mode="original" single="false" folio_number="480" conjoin="2" position="7" opposite="2"/>
    <leaf n="8" mode="original" single="false" folio_number="481" conjoin="1" position="8" opposite="1"/>
  </quire>
  <quire n="51">
    <leaf n="1" mode="original" single="false" folio_number="482" conjoin="12" position="1" opposite="12"/>
    <leaf n="2" mode="original" single="false" folio_number="483" conjoin="11" position="2" opposite="11"/>
    <leaf n="3" mode="original" single="false" folio_number="484" conjoin="10" position="3" opposite="10"/>
    <leaf n="4" mode="original" single="false" folio_number="485" conjoin="9" position="4" opposite="9"/>
    <leaf n="5" mode="original" single="false" folio_number="486" conjoin="8" position="5" opposite="8"/>
    <leaf n="6" mode="original" single="false" folio_number="487" conjoin="7" position="6" opposite="7"/>
    <leaf n="7" mode="original" single="false" folio_number="488" conjoin="6" position="7" opposite="6"/>
    <leaf n="8" mode="original" single="false" folio_number="489" conjoin="5" position="8" opposite="5"/>
    <leaf n="9" mode="original" single="false" folio_number="490" conjoin="4" position="9" opposite="4"/>
    <leaf n="10" mode="original" single="false" folio_number="491" conjoin="3" position="10" opposite="3"/>
    <leaf n="11" mode="original" single="false" folio_number="492" conjoin="2" position="11" opposite="2"/>
    <leaf n="12" mode="original" single="false" folio_number="493" conjoin="1" position="12" opposite="1"/>
  </quire>
  <quire n="52">
    <leaf n="" conjoin="9" position="1" opposite="10"/>
    <leaf n="1" mode="original" single="false" folio_number="494" conjoin="8" position="2" opposite="9"/>
    <leaf n="2" mode="original" single="false" folio_number="495" conjoin="7" position="3" opposite="8"/>
    <leaf n="3" mode="original" single="false" folio_number="496" conjoin="6" position="4" opposite="7"/>
    <leaf n="4" mode="original" single="false" folio_number="497" conjoin="5" position="5" opposite="6"/>
    <leaf n="5" mode="original" single="false" folio_number="498" conjoin="4" position="6" opposite="5"/>
    <leaf n="6" mode="original" single="false" folio_number="499" conjoin="3" position="7" opposite="4"/>
    <leaf n="7" mode="original" single="false" folio_number="500" conjoin="2" position="8" opposite="3"/>
    <leaf n="8" mode="original" single="false" folio_number="501" conjoin="1" position="9" opposite="2"/>
    <leaf n="9" mode="original" single="true" folio_number="502" conjoin="" position="10" opposite="1"/>
  </quire>
  <quire n="53">
    <leaf n="1" mode="original" single="false" folio_number="503" conjoin="10" position="1" opposite="10"/>
    <leaf n="2" mode="original" single="false" folio_number="504" conjoin="9" position="2" opposite="9"/>
    <leaf n="3" mode="original" single="false" folio_number="505" conjoin="8" position="3" opposite="8"/>
    <leaf n="4" mode="original" single="false" folio_number="506" conjoin="7" position="4" opposite="7"/>
    <leaf n="5" mode="original" single="false" folio_number="507" conjoin="6" position="5" opposite="6"/>
    <leaf n="6" mode="original" single="false" folio_number="508" conjoin="5" position="6" opposite="5"/>
    <leaf n="7" mode="original" single="false" folio_number="509" conjoin="4" position="7" opposite="4"/>
    <leaf n="8" mode="original" single="false" folio_number="510" conjoin="3" position="8" opposite="3"/>
    <leaf n="9" mode="original" single="false" folio_number="511" conjoin="2" position="9" opposite="2"/>
    <leaf n="10" mode="original" single="false" folio_number="512" conjoin="1" position="10" opposite="1"/>
  </quire>
  <quire n="54">
    <leaf n="1" mode="original" single="false" folio_number="513" conjoin="10" position="1" opposite="10"/>
    <leaf n="2" mode="original" single="false" folio_number="514" conjoin="9" position="2" opposite="9"/>
    <leaf n="3" mode="original" single="false" folio_number="515" conjoin="8" position="3" opposite="8"/>
    <leaf n="4" mode="original" single="false" folio_number="516" conjoin="7" position="4" opposite="7"/>
    <leaf n="5" mode="original" single="false" folio_number="517" conjoin="6" position="5" opposite="6"/>
    <leaf n="6" mode="original" single="false" folio_number="518" conjoin="5" position="6" opposite="5"/>
    <leaf n="7" mode="original" single="false" folio_number="519" conjoin="4" position="7" opposite="4"/>
    <leaf n="8" mode="original" single="false" folio_number="520" conjoin="3" position="8" opposite="3"/>
    <leaf n="9" mode="original" single="false" folio_number="521" conjoin="2" position="9" opposite="2"/>
    <leaf n="10" mode="original" single="false" folio_number="522" conjoin="1" position="10" opposite="1"/>
  </quire>
  <quire n="55">
    <leaf n="1" mode="original" single="false" folio_number="523" conjoin="10" position="1" opposite="10"/>
    <leaf n="2" mode="original" single="false" folio_number="524" conjoin="9" position="2" opposite="9"/>
    <leaf n="3" mode="original" single="false" folio_number="525" conjoin="8" position="3" opposite="8"/>
    <leaf n="4" mode="original" single="false" folio_number="526" conjoin="7" position="4" opposite="7"/>
    <leaf n="5" mode="original" single="false" folio_number="527" conjoin="6" position="5" opposite="6"/>
    <leaf n="6" mode="original" single="false" folio_number="528" conjoin="5" position="6" opposite="5"/>
    <leaf n="7" mode="original" single="false" folio_number="529" conjoin="4" position="7" opposite="4"/>
    <leaf n="8" mode="original" single="false" folio_number="530" conjoin="3" position="8" opposite="3"/>
    <leaf n="9" mode="original" single="false" folio_number="531" conjoin="2" position="9" opposite="2"/>
    <leaf n="10" mode="original" single="false" folio_number="532" conjoin="1" position="10" opposite="1"/>
  </quire>
  <quire n="56">
    <leaf n="1" mode="original" single="false" folio_number="533" conjoin="10" position="1" opposite="10"/>
    <leaf n="2" mode="original" single="false" folio_number="534" conjoin="9" position="2" opposite="9"/>
    <leaf n="3" mode="original" single="false" folio_number="535" conjoin="8" position="3" opposite="8"/>
    <leaf n="4" mode="original" single="false" folio_number="536" conjoin="7" position="4" opposite="7"/>
    <leaf n="5" mode="original" single="false" folio_number="537" conjoin="6" position="5" opposite="6"/>
    <leaf n="6" mode="original" single="false" folio_number="538" conjoin="5" position="6" opposite="5"/>
    <leaf n="7" mode="original" single="false" folio_number="539" conjoin="4" position="7" opposite="4"/>
    <leaf n="8" mode="original" single="false" folio_number="540" conjoin="3" position="8" opposite="3"/>
    <leaf n="9" mode="original" single="false" folio_number="541" conjoin="2" position="9" opposite="2"/>
    <leaf n="10" mode="original" single="false" folio_number="542" conjoin="1" position="10" opposite="1"/>
  </quire>
  <quire n="57">
    <leaf n="1" mode="original" single="false" folio_number="543" conjoin="10" position="1" opposite="10"/>
    <leaf n="2" mode="original" single="false" folio_number="544" conjoin="9" position="2" opposite="9"/>
    <leaf n="3" mode="original" single="false" folio_number="545" conjoin="8" position="3" opposite="8"/>
    <leaf n="4" mode="original" single="false" folio_number="546" conjoin="7" position="4" opposite="7"/>
    <leaf n="5" mode="original" single="false" folio_number="547" conjoin="6" position="5" opposite="6"/>
    <leaf n="6" mode="original" single="false" folio_number="548" conjoin="5" position="6" opposite="5"/>
    <leaf n="7" mode="original" single="false" folio_number="549" conjoin="4" position="7" opposite="4"/>
    <leaf n="8" mode="original" single="false" folio_number="550" conjoin="3" position="8" opposite="3"/>
    <leaf n="9" mode="original" single="false" folio_number="551" conjoin="2" position="9" opposite="2"/>
    <leaf n="10" mode="original" single="false" folio_number="552" conjoin="1" position="10" opposite="1"/>
  </quire>
  <quire n="58">
    <leaf n="1" mode="original" single="false" folio_number="553" conjoin="10" position="1" opposite="10"/>
    <leaf n="2" mode="original" single="false" folio_number="554" conjoin="9" position="2" opposite="9"/>
    <leaf n="3" mode="original" single="false" folio_number="555" conjoin="8" position="3" opposite="8"/>
    <leaf n="4" mode="original" single="false" folio_number="556" conjoin="7" position="4" opposite="7"/>
    <leaf n="5" mode="original" single="false" folio_number="557" conjoin="6" position="5" opposite="6"/>
    <leaf n="6" mode="original" single="false" folio_number="558" conjoin="5" position="6" opposite="5"/>
    <leaf n="7" mode="original" single="false" folio_number="559" conjoin="4" position="7" opposite="4"/>
    <leaf n="8" mode="original" single="false" folio_number="560" conjoin="3" position="8" opposite="3"/>
    <leaf n="9" mode="original" single="false" folio_number="561" conjoin="2" position="9" opposite="2"/>
    <leaf n="10" mode="original" single="false" folio_number="562" conjoin="1" position="10" opposite="1"/>
  </quire>
  <quire n="59">
    <leaf n="1" mode="original" single="false" folio_number="563" conjoin="10" position="1" opposite="10"/>
    <leaf n="2" mode="original" single="false" folio_number="564" conjoin="9" position="2" opposite="9"/>
    <leaf n="3" mode="original" single="false" folio_number="565" conjoin="8" position="3" opposite="8"/>
    <leaf n="4" mode="original" single="false" folio_number="566" conjoin="7" position="4" opposite="7"/>
    <leaf n="5" mode="original" single="false" folio_number="567" conjoin="6" position="5" opposite="6"/>
    <leaf n="6" mode="original" single="false" folio_number="568" conjoin="5" position="6" opposite="5"/>
    <leaf n="7" mode="original" single="false" folio_number="569" conjoin="4" position="7" opposite="4"/>
    <leaf n="8" mode="original" single="false" folio_number="570" conjoin="3" position="8" opposite="3"/>
    <leaf n="9" mode="original" single="false" folio_number="571" conjoin="2" position="9" opposite="2"/>
    <leaf n="10" mode="original" single="false" folio_number="572" conjoin="1" position="10" opposite="1"/>
  </quire>
  <quire n="60">
    <leaf n="1" mode="original" single="false" folio_number="573" conjoin="10" position="1" opposite="10"/>
    <leaf n="2" mode="original" single="false" folio_number="574" conjoin="9" position="2" opposite="9"/>
    <leaf n="3" mode="original" single="false" folio_number="575" conjoin="8" position="3" opposite="8"/>
    <leaf n="4" mode="original" single="false" folio_number="576" conjoin="7" position="4" opposite="7"/>
    <leaf n="5" mode="original" single="false" folio_number="577" conjoin="6" position="5" opposite="6"/>
    <leaf n="6" mode="original" single="false" folio_number="578" conjoin="5" position="6" opposite="5"/>
    <leaf n="7" mode="original" single="false" folio_number="579" conjoin="4" position="7" opposite="4"/>
    <leaf n="8" mode="original" single="false" folio_number="580" conjoin="3" position="8" opposite="3"/>
    <leaf n="9" mode="original" single="false" folio_number="581" conjoin="2" position="9" opposite="2"/>
    <leaf n="10" mode="original" single="false" folio_number="582" conjoin="1" position="10" opposite="1"/>
  </quire>
  <quire n="61">
    <leaf n="1" mode="original" single="false" folio_number="583" conjoin="10" position="1" opposite="10"/>
    <leaf n="2" mode="original" single="false" folio_number="584" conjoin="9" position="2" opposite="9"/>
    <leaf n="3" mode="original" single="false" folio_number="585" conjoin="8" position="3" opposite="8"/>
    <leaf n="4" mode="original" single="false" folio_number="586" conjoin="7" position="4" opposite="7"/>
    <leaf n="5" mode="original" single="false" folio_number="587" conjoin="6" position="5" opposite="6"/>
    <leaf n="6" mode="original" single="false" folio_number="588" conjoin="5" position="6" opposite="5"/>
    <leaf n="7" mode="original" single="false" folio_number="589" conjoin="4" position="7" opposite="4"/>
    <leaf n="8" mode="original" single="false" folio_number="590" conjoin="3" position="8" opposite="3"/>
    <leaf n="9" mode="original" single="false" folio_number="591" conjoin="2" position="9" opposite="2"/>
    <leaf n="10" mode="original" single="false" folio_number="592" conjoin="1" position="10" opposite="1"/>
  </quire>
  <quire n="62">
    <leaf n="1" mode="original" single="false" folio_number="593" conjoin="10" position="1" opposite="10"/>
    <leaf n="2" mode="original" single="false" folio_number="594" conjoin="9" position="2" opposite="9"/>
    <leaf n="3" mode="original" single="false" folio_number="595" conjoin="8" position="3" opposite="8"/>
    <leaf n="4" mode="original" single="false" folio_number="596" conjoin="7" position="4" opposite="7"/>
    <leaf n="5" mode="original" single="false" folio_number="597" conjoin="6" position="5" opposite="6"/>
    <leaf n="6" mode="original" single="false" folio_number="598" conjoin="5" position="6" opposite="5"/>
    <leaf n="7" mode="original" single="false" folio_number="599" conjoin="4" position="7" opposite="4"/>
    <leaf n="8" mode="original" single="false" folio_number="600" conjoin="3" position="8" opposite="3"/>
    <leaf n="9" mode="original" single="false" folio_number="601" conjoin="2" position="9" opposite="2"/>
    <leaf n="10" mode="original" single="false" folio_number="602" conjoin="1" position="10" opposite="1"/>
  </quire>
  <quire n="63">
    <leaf n="1" mode="original" single="false" folio_number="603" conjoin="10" position="1" opposite="10"/>
    <leaf n="2" mode="original" single="false" folio_number="604" conjoin="9" position="2" opposite="9"/>
    <leaf n="3" mode="original" single="false" folio_number="605" conjoin="8" position="3" opposite="8"/>
    <leaf n="4" mode="original" single="false" folio_number="606" conjoin="7" position="4" opposite="7"/>
    <leaf n="5" mode="original" single="false" folio_number="607" conjoin="6" position="5" opposite="6"/>
    <leaf n="6" mode="original" single="false" folio_number="608" conjoin="5" position="6" opposite="5"/>
    <leaf n="7" mode="original" single="false" folio_number="609" conjoin="4" position="7" opposite="4"/>
    <leaf n="8" mode="original" single="false" folio_number="610" conjoin="3" position="8" opposite="3"/>
    <leaf n="9" mode="original" single="false" folio_number="611" conjoin="2" position="9" opposite="2"/>
    <leaf n="10" mode="original" single="false" folio_number="612" conjoin="1" position="10" opposite="1"/>
  </quire>
  <quire n="64">
    <leaf n="1" mode="original" single="false" folio_number="613" conjoin="10" position="1" opposite="10"/>
    <leaf n="2" mode="original" single="false" folio_number="614" conjoin="9" position="2" opposite="9"/>
    <leaf n="3" mode="original" single="false" folio_number="615" conjoin="8" position="3" opposite="8"/>
    <leaf n="4" mode="original" single="false" folio_number="616" conjoin="7" position="4" opposite="7"/>
    <leaf n="5" mode="original" single="false" folio_number="617" conjoin="6" position="5" opposite="6"/>
    <leaf n="6" mode="original" single="false" folio_number="618" conjoin="5" position="6" opposite="5"/>
    <leaf n="7" mode="original" single="false" folio_number="619" conjoin="4" position="7" opposite="4"/>
    <leaf n="8" mode="original" single="false" folio_number="620" conjoin="3" position="8" opposite="3"/>
    <leaf n="9" mode="original" single="false" folio_number="621" conjoin="2" position="9" opposite="2"/>
    <leaf n="10" mode="original" single="false" folio_number="622" conjoin="1" position="10" opposite="1"/>
  </quire>
  <quire n="65">
    <leaf n="1" mode="original" single="false" folio_number="623" conjoin="10" position="1" opposite="10"/>
    <leaf n="2" mode="original" single="false" folio_number="624" conjoin="9" position="2" opposite="9"/>
    <leaf n="3" mode="original" single="false" folio_number="625" conjoin="8" position="3" opposite="8"/>
    <leaf n="4" mode="original" single="false" folio_number="626" conjoin="7" position="4" opposite="7"/>
    <leaf n="5" mode="original" single="false" folio_number="627" conjoin="6" position="5" opposite="6"/>
    <leaf n="6" mode="original" single="false" folio_number="628" conjoin="5" position="6" opposite="5"/>
    <leaf n="7" mode="original" single="false" folio_number="629" conjoin="4" position="7" opposite="4"/>
    <leaf n="8" mode="original" single="false" folio_number="630" conjoin="3" position="8" opposite="3"/>
    <leaf n="9" mode="original" single="false" folio_number="631" conjoin="2" position="9" opposite="2"/>
    <leaf n="10" mode="original" single="false" folio_number="632" conjoin="1" position="10" opposite="1"/>
  </quire>
  <quire n="66">
    <leaf n="1" mode="original" single="false" folio_number="633" conjoin="10" position="1" opposite="10"/>
    <leaf n="2" mode="original" single="false" folio_number="634" conjoin="9" position="2" opposite="9"/>
    <leaf n="3" mode="original" single="false" folio_number="635" conjoin="8" position="3" opposite="8"/>
    <leaf n="4" mode="original" single="false" folio_number="636" conjoin="7" position="4" opposite="7"/>
    <leaf n="5" mode="original" single="false" folio_number="637" conjoin="6" position="5" opposite="6"/>
    <leaf n="6" mode="original" single="false" folio_number="638" conjoin="5" position="6" opposite="5"/>
    <leaf n="7" mode="original" single="false" folio_number="639" conjoin="4" position="7" opposite="4"/>
    <leaf n="8" mode="original" single="false" folio_number="640" conjoin="3" position="8" opposite="3"/>
    <leaf n="9" mode="original" single="false" folio_number="641" conjoin="2" position="9" opposite="2"/>
    <leaf n="10" mode="original" single="false" folio_number="642" conjoin="1" position="10" opposite="1"/>
  </quire>
  <quire n="67">
    <leaf n="1" mode="original" single="false" folio_number="643" conjoin="10" position="1" opposite="10"/>
    <leaf n="2" mode="original" single="false" folio_number="644" conjoin="9" position="2" opposite="9"/>
    <leaf n="3" mode="original" single="false" folio_number="645" conjoin="8" position="3" opposite="8"/>
    <leaf n="4" mode="original" single="false" folio_number="646" conjoin="7" position="4" opposite="7"/>
    <leaf n="5" mode="original" single="false" folio_number="647" conjoin="6" position="5" opposite="6"/>
    <leaf n="6" mode="original" single="false" folio_number="648" conjoin="5" position="6" opposite="5"/>
    <leaf n="7" mode="original" single="false" folio_number="649" conjoin="4" position="7" opposite="4"/>
    <leaf n="8" mode="original" single="false" folio_number="650" conjoin="3" position="8" opposite="3"/>
    <leaf n="9" mode="original" single="false" folio_number="651" conjoin="2" position="9" opposite="2"/>
    <leaf n="10" mode="original" single="false" folio_number="652" conjoin="1" position="10" opposite="1"/>
  </quire>
  <quire n="68">
    <leaf n="1" mode="original" single="false" folio_number="653" conjoin="10" position="1" opposite="10"/>
    <leaf n="2" mode="original" single="false" folio_number="654" conjoin="9" position="2" opposite="9"/>
    <leaf n="3" mode="original" single="false" folio_number="655" conjoin="8" position="3" opposite="8"/>
    <leaf n="4" mode="original" single="false" folio_number="656" conjoin="7" position="4" opposite="7"/>
    <leaf n="5" mode="original" single="false" folio_number="657" conjoin="6" position="5" opposite="6"/>
    <leaf n="6" mode="original" single="false" folio_number="658" conjoin="5" position="6" opposite="5"/>
    <leaf n="7" mode="original" single="false" folio_number="659" conjoin="4" position="7" opposite="4"/>
    <leaf n="8" mode="original" single="false" folio_number="660" conjoin="3" position="8" opposite="3"/>
    <leaf n="9" mode="original" single="false" folio_number="661" conjoin="2" position="9" opposite="2"/>
    <leaf n="10" mode="original" single="false" folio_number="662" conjoin="1" position="10" opposite="1"/>
  </quire>
  <quire n="69">
    <leaf n="1" mode="original" single="false" folio_number="663" conjoin="10" position="1" opposite="10"/>
    <leaf n="2" mode="original" single="false" folio_number="664" conjoin="9" position="2" opposite="9"/>
    <leaf n="3" mode="original" single="false" folio_number="665" conjoin="8" position="3" opposite="8"/>
    <leaf n="4" mode="original" single="false" folio_number="666" conjoin="7" position="4" opposite="7"/>
    <leaf n="5" mode="original" single="false" folio_number="667" conjoin="6" position="5" opposite="6"/>
    <leaf n="6" mode="original" single="false" folio_number="668" conjoin="5" position="6" opposite="5"/>
    <leaf n="7" mode="original" single="false" folio_number="669" conjoin="4" position="7" opposite="4"/>
    <leaf n="8" mode="original" single="false" folio_number="670" conjoin="3" position="8" opposite="3"/>
    <leaf n="9" mode="original" single="false" folio_number="671" conjoin="2" position="9" opposite="2"/>
    <leaf n="10" mode="original" single="false" folio_number="672" conjoin="1" position="10" opposite="1"/>
  </quire>
  <quire n="70">
    <leaf n="1" mode="original" single="false" folio_number="673" conjoin="10" position="1" opposite="10"/>
    <leaf n="2" mode="original" single="false" folio_number="674" conjoin="9" position="2" opposite="9"/>
    <leaf n="3" mode="original" single="false" folio_number="675" conjoin="8" position="3" opposite="8"/>
    <leaf n="4" mode="original" single="false" folio_number="676" conjoin="7" position="4" opposite="7"/>
    <leaf n="5" mode="original" single="false" folio_number="677" conjoin="6" position="5" opposite="6"/>
    <leaf n="6" mode="original" single="false" folio_number="678" conjoin="5" position="6" opposite="5"/>
    <leaf n="7" mode="original" single="false" folio_number="679" conjoin="4" position="7" opposite="4"/>
    <leaf n="8" mode="original" single="false" folio_number="680" conjoin="3" position="8" opposite="3"/>
    <leaf n="9" mode="original" single="false" folio_number="681" conjoin="2" position="9" opposite="2"/>
    <leaf n="10" mode="original" single="false" folio_number="682" conjoin="1" position="10" opposite="1"/>
  </quire>
  <quire n="71">
    <leaf n="1" mode="original" single="false" folio_number="683" conjoin="10" position="1" opposite="10"/>
    <leaf n="2" mode="original" single="false" folio_number="684" conjoin="9" position="2" opposite="9"/>
    <leaf n="3" mode="original" single="false" folio_number="685" conjoin="8" position="3" opposite="8"/>
    <leaf n="4" mode="original" single="false" folio_number="686" conjoin="7" position="4" opposite="7"/>
    <leaf n="5" mode="original" single="false" folio_number="687" conjoin="6" position="5" opposite="6"/>
    <leaf n="6" mode="original" single="false" folio_number="688" conjoin="5" position="6" opposite="5"/>
    <leaf n="7" mode="original" single="false" folio_number="689" conjoin="4" position="7" opposite="4"/>
    <leaf n="8" mode="original" single="false" folio_number="690" conjoin="3" position="8" opposite="3"/>
    <leaf n="9" mode="original" single="false" folio_number="691" conjoin="2" position="9" opposite="2"/>
    <leaf n="10" mode="original" single="false" folio_number="692" conjoin="1" position="10" opposite="1"/>
  </quire>
  <quire n="72">
    <leaf n="1" mode="original" single="false" folio_number="693" conjoin="10" position="1" opposite="10"/>
    <leaf n="2" mode="original" single="false" folio_number="694" conjoin="9" position="2" opposite="9"/>
    <leaf n="3" mode="original" single="false" folio_number="695" conjoin="8" position="3" opposite="8"/>
    <leaf n="4" mode="original" single="false" folio_number="696" conjoin="7" position="4" opposite="7"/>
    <leaf n="5" mode="original" single="false" folio_number="697" conjoin="6" position="5" opposite="6"/>
    <leaf n="6" mode="original" single="false" folio_number="698" conjoin="5" position="6" opposite="5"/>
    <leaf n="7" mode="original" single="false" folio_number="699" conjoin="4" position="7" opposite="4"/>
    <leaf n="8" mode="original" single="false" folio_number="700" conjoin="3" position="8" opposite="3"/>
    <leaf n="9" mode="original" single="false" folio_number="701" conjoin="2" position="9" opposite="2"/>
    <leaf n="10" mode="original" single="false" folio_number="702" conjoin="1" position="10" opposite="1"/>
  </quire>
  <quire n="73">
    <leaf n="1" mode="original" single="false" folio_number="703" conjoin="10" position="1" opposite="10"/>
    <leaf n="2" mode="original" single="false" folio_number="704" conjoin="9" position="2" opposite="9"/>
    <leaf n="3" mode="original" single="false" folio_number="705" conjoin="8" position="3" opposite="8"/>
    <leaf n="4" mode="original" single="false" folio_number="706" conjoin="7" position="4" opposite="7"/>
    <leaf n="5" mode="original" single="false" folio_number="707" conjoin="6" position="5" opposite="6"/>
    <leaf n="6" mode="original" single="false" folio_number="708" conjoin="5" position="6" opposite="5"/>
    <leaf n="7" mode="original" single="false" folio_number="709" conjoin="4" position="7" opposite="4"/>
    <leaf n="8" mode="original" single="false" folio_number="710" conjoin="3" position="8" opposite="3"/>
    <leaf n="9" mode="original" single="false" folio_number="711" conjoin="2" position="9" opposite="2"/>
    <leaf n="10" mode="original" single="false" folio_number="712" conjoin="1" position="10" opposite="1"/>
  </quire>
  <quire n="74">
    <leaf n="1" mode="original" single="false" folio_number="713" conjoin="10" position="1" opposite="10"/>
    <leaf n="2" mode="original" single="false" folio_number="714" conjoin="9" position="2" opposite="9"/>
    <leaf n="3" mode="original" single="false" folio_number="715" conjoin="8" position="3" opposite="8"/>
    <leaf n="4" mode="original" single="false" folio_number="716" conjoin="7" position="4" opposite="7"/>
    <leaf n="5" mode="original" single="false" folio_number="717" conjoin="6" position="5" opposite="6"/>
    <leaf n="6" mode="original" single="false" folio_number="718" conjoin="5" position="6" opposite="5"/>
    <leaf n="7" mode="original" single="false" folio_number="719" conjoin="4" position="7" opposite="4"/>
    <leaf n="8" mode="original" single="false" folio_number="720" conjoin="3" position="8" opposite="3"/>
    <leaf n="9" mode="original" single="false" folio_number="721" conjoin="2" position="9" opposite="2"/>
    <leaf n="10" mode="original" single="false" folio_number="722" conjoin="1" position="10" opposite="1"/>
  </quire>
  <quire n="75">
    <leaf n="1" mode="original" single="false" folio_number="723" conjoin="10" position="1" opposite="10"/>
    <leaf n="2" mode="original" single="false" folio_number="724" conjoin="9" position="2" opposite="9"/>
    <leaf n="3" mode="original" single="false" folio_number="725" conjoin="8" position="3" opposite="8"/>
    <leaf n="4" mode="original" single="false" folio_number="726" conjoin="7" position="4" opposite="7"/>
    <leaf n="5" mode="original" single="false" folio_number="727" conjoin="6" position="5" opposite="6"/>
    <leaf n="6" mode="original" single="false" folio_number="728" conjoin="5" position="6" opposite="5"/>
    <leaf n="7" mode="original" single="false" folio_number="729" conjoin="4" position="7" opposite="4"/>
    <leaf n="8" mode="original" single="false" folio_number="730" conjoin="3" position="8" opposite="3"/>
    <leaf n="9" mode="original" single="false" folio_number="731" conjoin="2" position="9" opposite="2"/>
    <leaf n="10" mode="original" single="false" folio_number="732" conjoin="1" position="10" opposite="1"/>
  </quire>
  <quire n="76">
    <leaf n="1" mode="original" single="false" folio_number="733" conjoin="10" position="1" opposite="10"/>
    <leaf n="2" mode="original" single="false" folio_number="734" conjoin="9" position="2" opposite="9"/>
    <leaf n="3" mode="original" single="false" folio_number="735" conjoin="8" position="3" opposite="8"/>
    <leaf n="4" mode="original" single="false" folio_number="736" conjoin="7" position="4" opposite="7"/>
    <leaf n="5" mode="original" single="false" folio_number="737" conjoin="6" position="5" opposite="6"/>
    <leaf n="6" mode="original" single="false" folio_number="738" conjoin="5" position="6" opposite="5"/>
    <leaf n="7" mode="original" single="false" folio_number="739" conjoin="4" position="7" opposite="4"/>
    <leaf n="8" mode="original" single="false" folio_number="740" conjoin="3" position="8" opposite="3"/>
    <leaf n="9" mode="original" single="false" folio_number="741" conjoin="2" position="9" opposite="2"/>
    <leaf n="10" mode="original" single="false" folio_number="742" conjoin="1" position="10" opposite="1"/>
  </quire>
  <quire n="77">
    <leaf n="1" mode="original" single="false" folio_number="743" conjoin="10" position="1" opposite="10"/>
    <leaf n="2" mode="original" single="false" folio_number="744" conjoin="9" position="2" opposite="9"/>
    <leaf n="3" mode="original" single="false" folio_number="745" conjoin="8" position="3" opposite="8"/>
    <leaf n="4" mode="original" single="false" folio_number="746" conjoin="7" position="4" opposite="7"/>
    <leaf n="5" mode="original" single="false" folio_number="747" conjoin="6" position="5" opposite="6"/>
    <leaf n="6" mode="original" single="false" folio_number="748" conjoin="5" position="6" opposite="5"/>
    <leaf n="7" mode="original" single="false" folio_number="749" conjoin="4" position="7" opposite="4"/>
    <leaf n="8" mode="original" single="false" folio_number="750" conjoin="3" position="8" opposite="3"/>
    <leaf n="9" mode="original" single="false" folio_number="751" conjoin="2" position="9" opposite="2"/>
    <leaf n="10" mode="original" single="false" folio_number="752" conjoin="1" position="10" opposite="1"/>
  </quire>
  <quire n="78">
    <leaf n="" conjoin="1" position="1" opposite="4"/>
    <leaf n="1" mode="original" single="true" folio_number="753" conjoin="" position="2" opposite="3"/>
    <leaf n="2" mode="original" single="false" folio_number="754" conjoin="3" position="3" opposite="2"/>
    <leaf n="3" mode="original" single="false" folio_number="755" conjoin="2" position="4" opposite="1"/>
  </quire>
  <quire n="79">
    <leaf n="1" mode="original" single="false" folio_number="756" conjoin="4" position="1" opposite="4"/>
    <leaf n="2" mode="original" single="false" folio_number="757" conjoin="3" position="2" opposite="3"/>
    <leaf n="3" mode="original" single="false" folio_number="758" conjoin="2" position="3" opposite="2"/>
    <leaf n="4" mode="original" single="false" folio_number="759" conjoin="1" position="4" opposite="1"/>
  </quire>
  <quire n="80">
    <leaf n="1" mode="original" single="false" folio_number="760" conjoin="10" position="1" opposite="10"/>
    <leaf n="2" mode="original" single="false" folio_number="761" conjoin="9" position="2" opposite="9"/>
    <leaf n="3" mode="original" single="false" folio_number="762" conjoin="8" position="3" opposite="8"/>
    <leaf n="4" mode="original" single="false" folio_number="763" conjoin="7" position="4" opposite="7"/>
    <leaf n="5" mode="original" single="false" folio_number="764" conjoin="6" position="5" opposite="6"/>
    <leaf n="6" mode="original" single="false" folio_number="765" conjoin="5" position="6" opposite="5"/>
    <leaf n="7" mode="original" single="false" folio_number="766" conjoin="4" position="7" opposite="4"/>
    <leaf n="8" mode="original" single="false" folio_number="767" conjoin="3" position="8" opposite="3"/>
    <leaf n="9" mode="original" single="false" folio_number="768" conjoin="2" position="9" opposite="2"/>
    <leaf n="10" mode="original" single="false" folio_number="769" conjoin="1" position="10" opposite="1"/>
  </quire>
</manuscript>
